langchain_cloro/__init__.py
langchain_cloro/_utilities.py
langchain_cloro/py.typed
langchain_cloro/tools.py
langchain_cloro/utils.py
langchain_cloro-0.2.2.dist-info/METADATA
langchain_cloro-0.2.2.dist-info/WHEEL
langchain_cloro-0.2.2.dist-info/licenses/LICENSE
langchain_cloro-0.2.2.dist-info/RECORD
