Metadata-Version: 2.4
Name: langchain-cloro
Version: 0.2.2
Summary: An integration package connecting cloro.dev and LangChain
Project-URL: Homepage, https://docs.cloro.dev
Project-URL: Documentation, https://docs.cloro.dev
Project-URL: Source, https://github.com/cloro-dev/langchain-cloro
Project-URL: Changelog, https://github.com/cloro-dev/langchain-cloro/releases
Project-URL: Repository, https://github.com/cloro-dev/langchain-cloro
License: MIT
License-File: LICENSE
Requires-Python: <4.0.0,>=3.10.0
Requires-Dist: httpx<1.0.0,>=0.25.0
Requires-Dist: langchain-core<1.0.0,>=0.1.0
